{
	"required": true,
	"package": "com.reachcrafting.client.mixin",
	"compatibilityLevel": "JAVA_21",
	"client": [
		"AbstractContainerMenuMixin",
		"AbstractContainerScreenMixin",
		"AbstractRecipeBookScreenAccessor",
		"ClientRecipeBookAccessor",
		"EditBoxAccessor",
		"KeyMappingAccessor",
		"MinecraftInteractionBlockMixin",
		"MultiPlayerGameModeMixin",
		"OverlayRecipeButtonMixin",
		"OverlayRecipeButtonAccessor",
		"OverlayRecipeComponentAccessor",
		"OverlayRecipeComponentMixin",
		"PlayerSecondaryUseMixin",
		"PopupScreenAccessor",
		"PopupScreenMixin",
		"RecipeButtonMixin",
		"RecipeBookComponentAccessor",
		"RecipeBookPageAccessor",
		"RecipeBookPageMixin",
		"RecipeBookComponentMixin",
		"AbstractContainerScreenAccessor"
	],
	"injectors": {
		"defaultRequire": 1
	},
	"overwrites": {
		"requireAnnotations": true
	}
}
